{
  "name": "Landing — SaaS",
  "slug": "landing-saas",
  "description": "Full landing page for a SaaS product. Composes hero + social proof + three-pillar value prop + alternating feature deep-dives + stats + testimonial slider + final CTA. Feature-heavy storytelling flow, clean sans-serif defaults.",
  "category": "landing",
  "tags": ["landing", "home", "saas", "product", "conversion", "feature-deep-dive", "stats", "full-page"],
  "layout": "hero-first",
  "default_palette": "modern-navy",
  "kits_used": [
    "header-classic",
    "hero-split",
    "logo-wall",
    "feature-grid",
    "feature-alternating",
    "stats-counter",
    "testimonial-slider",
    "cta-banner",
    "footer-minimal"
  ],
  "files": {
    "php": ["section.php"],
    "css": ["section.css"]
  },
  "variables": {
    "productName": {
      "label": "Product name",
      "type": "string",
      "default": "Atlas"
    },
    "heroEyebrow": {
      "label": "Hero eyebrow",
      "type": "string",
      "default": "New · v2.0 just launched"
    },
    "heroTitle": {
      "label": "Hero headline",
      "type": "string",
      "default": "Ship your next release without breaking the last one"
    },
    "heroBody": {
      "label": "Hero supporting text",
      "type": "string",
      "default": "A release platform that catches regressions before they reach prod. Integrates with your existing stack in minutes, not weeks."
    },
    "heroPrimaryLabel": {
      "label": "Primary CTA",
      "type": "string",
      "default": "Start free"
    },
    "heroSecondaryLabel": {
      "label": "Secondary CTA",
      "type": "string",
      "default": "Watch a demo"
    },
    "logoWallTitle": {
      "label": "Logo wall title",
      "type": "string",
      "default": "Trusted by teams shipping at scale"
    },
    "pillarsTitle": {
      "label": "Value-prop title",
      "type": "string",
      "default": "Everything your release pipeline needs"
    },
    "pillarsSubtitle": {
      "label": "Value-prop subtitle",
      "type": "string",
      "default": "Six capabilities, one platform, zero yak-shaving"
    },
    "featuresTitle": {
      "label": "Feature deep-dive title",
      "type": "string",
      "default": "Built for the way shipping actually works"
    },
    "featuresSubtitle": {
      "label": "Feature deep-dive subtitle",
      "type": "string",
      "default": "Each capability, explained in detail"
    },
    "statsTitle": {
      "label": "Stats title",
      "type": "string",
      "default": "The numbers teams see after switching"
    },
    "testimonialsTitle": {
      "label": "Testimonials title",
      "type": "string",
      "default": "What our customers are saying"
    },
    "ctaTitle": {
      "label": "Final CTA headline",
      "type": "string",
      "default": "Start shipping with confidence"
    },
    "ctaSubtitle": {
      "label": "Final CTA subtitle",
      "type": "string",
      "default": "Free for teams up to 10. No credit card required."
    },
    "ctaPrimaryLabel": {
      "label": "Final CTA primary",
      "type": "string",
      "default": "Start free"
    },
    "ctaSecondaryLabel": {
      "label": "Final CTA secondary",
      "type": "string",
      "default": "Talk to sales"
    }
  }
}
